quraite/__init__.py
quraite/adapters/__init__.py
quraite/adapters/agno_adapter.py
quraite/adapters/base.py
quraite/adapters/bedrock_agents_adapter.py
quraite/adapters/flowise_adapter.py
quraite/adapters/google_adk_adapter.py
quraite/adapters/http_adapter.py
quraite/adapters/langchain_adapter.py
quraite/adapters/langchain_server_adapter.py
quraite/adapters/langflow_adapter.py
quraite/adapters/n8n_adapter.py
quraite/adapters/openai_agents_adapter.py
quraite/adapters/pydantic_ai_adapter.py
quraite/adapters/smolagents_adapter.py
quraite/logger.py
quraite/schema/__init__.py
quraite/schema/message.py
quraite/schema/response.py
quraite/serve/__init__.py
quraite/serve/cloudflared.py
quraite/serve/local_agent.py
quraite/traces/traces_adk_openinference.json
quraite/traces/traces_agno_multi_agent.json
quraite/traces/traces_agno_openinference.json
quraite/traces/traces_crewai_openinference.json
quraite/traces/traces_langgraph_openinference.json
quraite/traces/traces_langgraph_openinference_multi_agent.json
quraite/traces/traces_langgraph_traceloop.json
quraite/traces/traces_openai_agents_multi_agent_1.json
quraite/traces/traces_openai_agents_openinference.json
quraite/traces/traces_pydantic_openinference.json
quraite/traces/traces_pydantic_openinference_multi_agent_1.json
quraite/traces/traces_pydantic_openinference_multi_agent_2.json
quraite/traces/traces_smol_agents_openinference.json
quraite/traces/traces_smol_agents_tool_calling_openinference.json
quraite/tracing/__init__.py
quraite/tracing/constants.py
quraite/tracing/span_exporter.py
quraite/tracing/span_processor.py
quraite/tracing/tool_extractors.py
quraite/tracing/trace.py
quraite/tracing/types.py
quraite/tracing/utils.py
quraite/utils/__init__.py
quraite/utils/json_utils.py
quraite-0.1.3.dist-info/WHEEL
quraite-0.1.3.dist-info/METADATA
quraite-0.1.3.dist-info/RECORD
